setup.py
binaryheap/__init__.py
binaryheap/core.py
binaryheap.egg-info/PKG-INFO
binaryheap.egg-info/SOURCES.txt
binaryheap.egg-info/dependency_links.txt
binaryheap.egg-info/top_level.txt