Metadata-Version: 1.0
Name: binaryheap
Version: 1.0.0
Summary: This is implementation of binary heap.
Home-page: https://github.com/emludei/binaryheap
Author: emludei
Author-email: incontrol64@yandex.ru
License: Apache License 2.0
Platform: UNKNOWN
